moisten_plot/__init__.py
moisten_plot/_colormap.py
moisten_plot/_core.py
moisten_plot/_font_properties.py
moisten_plot/_interface.py
moisten_plot/_quiver.py
moisten_plot/axes_tools.py
moisten_plot/length_unit.py
moisten_plot/moiCmap.py
moisten_plot/moi_figure.py
moisten_plot-0.1.3.dist-info/licenses/LICENSE
moisten_plot-0.1.3.dist-info/METADATA
moisten_plot-0.1.3.dist-info/WHEEL
moisten_plot-0.1.3.dist-info/top_level.txt
moisten_plot-0.1.3.dist-info/RECORD
