Metadata-Version: 2.4
Name: moisten-plot
Version: 0.1.3
Summary: A module to improve matplotlib plot and make it easier to use. This is a part of moisten package series.
Project-URL: Repository, https://gitee.com/lilidream/moisten_plot
Requires-Python: >=3.12
License-File: LICENSE
Requires-Dist: cartopy>=0.22
Requires-Dist: matplotlib>=3.10.0
Requires-Dist: rich>=13.8.0
Requires-Dist: scipy>=0.14.0
Dynamic: license-file
